discord_easy_commands/__init__.py
discord_easy_commands-0.1.1.dist-info/METADATA
discord_easy_commands-0.1.1.dist-info/WHEEL
discord_easy_commands-0.1.1.dist-info/top_level.txt
discord_easy_commands-0.1.1.dist-info/RECORD
