Metadata-Version: 2.1
Name: discord-easy-commands
Version: 0.1.1
Summary: Custom Code
Home-page: https://github.com/linkfy
Author: Linkfy
Author-email: demo@linkfy.xyz
License: UNKNOWN
Platform: UNKNOWN
Requires-Dist: Flask
Requires-Dist: discord.py
